{
  "UID": "f91863e3b92d4a59903b24fdf80a5c15",
  "children": [{
    "UID": "f66c63d0ab5342d5b18f91b8a93c3e6d",
    "children": [{
      "UID": "7eb7affca097477298fc6e3117830667",
      "children": [],
      "hitBoxes": [],
      "properties": {
        "listeners": {},
        "gridsize": 50,
        "scripts": {"holderScript": {}}
      }
    }],
    "hitBoxes": [],
    "properties": {
      "mapwidth": 5000,
      "listeners": {},
      "gridsize": 50,
      "mapheight": 5000,
      "scripts": {"mapScript": {}},
      "levelname": "level 1"
    }
  }],
  "hitBoxes": [],
  "properties": {}
}