{
  "UID": "fe698be1380d426db3d01aa07c60fe80",
  "children": [{
    "UID": "e134a333368240eda6d7a638ae2c8ecf",
    "children": [{
      "UID": "af297de0de334ce78f7516a66ab5b67a",
      "children": [],
      "hitBoxes": [],
      "properties": {
        "listeners": {},
        "gridsize": 50,
        "scripts": {"holderScript": {}}
      }
    }],
    "hitBoxes": [],
    "properties": {
      "cameraXpos": 0,
      "mapwidth": 5000,
      "cameraYpos": 0,
      "cameraHeight": 500,
      "listeners": {},
      "gridsize": 50,
      "mapheight": 5000,
      "cameraWidth": 500,
      "scripts": {
        "hudScript": {},
        "mapScript": {}
      },
      "levelname": "level 1"
    }
  }],
  "hitBoxes": [],
  "properties": {}
}