{
  "UID": "6648c739a04944e197e868daff781fe0",
  "children": [{
    "UID": "9ee5d5f303bd4ff999345200dbe3cd10",
    "children": [{
      "UID": "e354b73887fe40d496fbb92942ba6879",
      "children": [],
      "hitBoxes": [],
      "properties": {
        "listeners": {},
        "gridsize": 50,
        "scripts": {"holderScript": {}}
      }
    }],
    "hitBoxes": [],
    "properties": {
      "cameraXpos": 0,
      "mapwidth": 5000,
      "cameraYpos": 0,
      "cameraHeight": 500,
      "listeners": {},
      "gridsize": 50,
      "mapheight": 5000,
      "cameraWidth": 500,
      "scripts": {"mapScript": {}},
      "levelname": "level 1"
    }
  }],
  "hitBoxes": [],
  "properties": {}
}